Metadata-Version: 2.1
Name: noteql
Version: 0.7.1
Summary: Write sql in a notbook
Home-page: https://github.com/OpenDataServices/noteql
Author: David Raznick
Author-email: david.raznick@opendataservices.coop
License: UNKNOWN
Platform: UNKNOWN
License-File: LICENSE
